unifi_wlc_api/__init__.py
unifi_wlc_api/api.py
unifi_wlc_api/setup.py
unifi_wlc_api/unifi_wlc_api/__init__.py
unifi_wlc_api/unifi_wlc_api/api.py
unifi_wlc_api-0.1.0.dist-info/licenses/LICENSE
unifi_wlc_api-0.1.0.dist-info/METADATA
unifi_wlc_api-0.1.0.dist-info/WHEEL
unifi_wlc_api-0.1.0.dist-info/top_level.txt
unifi_wlc_api-0.1.0.dist-info/RECORD
