Metadata-Version: 2.4
Name: unifi_wlc_api
Version: 0.1.0
Summary: Python API client for Ubiquiti UniFi Controller
Home-page: https://github.com/zhuyuehui1993/unifi_wlc_api
Author: yuehui
Author-email: 745397238@qq.com
Classifier: Programming Language :: Python :: 3
Classifier: License :: OSI Approved :: MIT License
Classifier: Operating System :: OS Independent
Requires-Python: >=3.6
License-File: LICENSE
Requires-Dist: requests>=2.25.0
Dynamic: author
Dynamic: author-email
Dynamic: classifier
Dynamic: description
Dynamic: description-content-type
Dynamic: home-page
Dynamic: license-file
Dynamic: requires-dist
Dynamic: requires-python
Dynamic: summary
